{
  "id": "714914678502",
  "name": "paper-mhc-synthesis",
  "topic": "paper-mhc",
  "chain_position": 10,
  "depends_on": "paper-mhc-overview",
  "description": "Use web_search to search for 'mHC manifold-constrained hyper-connections paper identity mapping scalability'. Results heavily overlap with earlier searches. Synthesize the residual connection innovation landscape: HC, mHC, AttnRes — which approach is most promising and why? Keep response under 100 words.",
  "search_query": "mHC manifold-constrained hyper-connections paper identity mapping scalability",
  "category": "summarization",
  "difficulty": "medium",
  "expected_steps": 3,
  "skills_required": [
    "web_search"
  ],
  "skills_info": [
    {
      "slug": "web_search",
      "displayName": "Web Search",
      "category": "search_web"
    }
  ],
  "num_skills": 1,
  "ground_truth": null
}