{
  "id": "9d32b07f0946",
  "name": "paper-hyperconn-implementation",
  "topic": "paper-hyperconn",
  "chain_position": 9,
  "depends_on": "paper-hyperconn-overview",
  "description": "Use web_search to search for 'Hyper-Connections paper residual connections alternative deep learning'. Results overlap with earlier searches. What are the key implementation details and hyperparameters for hyper-connections? List the main practical considerations. Keep response under 100 words.",
  "search_query": "Hyper-Connections paper residual connections alternative deep learning",
  "category": "planning",
  "difficulty": "medium",
  "expected_steps": 3,
  "skills_required": [
    "web_search"
  ],
  "skills_info": [
    {
      "slug": "web_search",
      "displayName": "Web Search",
      "category": "search_web"
    }
  ],
  "num_skills": 1,
  "ground_truth": null
}